{
    "py/object": "datatable_helper.Combined_LTS_Problem_test",
    "data": {
        "AlgorithmsTest_FitPeaksTest": {
            "py/object": "datatable_helper.Combined_LTS_Problem_test_entry",
            "test_name": "AlgorithmsTest_FitPeaksTest",
            "agent_name": "Windows",
            "past_failed_outcome": {
                "main_nightly_deployment_prototype_430": "Flake",
                "pull_requests-conda-windows_475": "Flake",
                "pull_requests-conda-windows_491": "Flake",
                "pull_requests-conda-windows_493": "Flake",
                "pull_requests-conda-windows_504": "Flake",
                "pull_requests-conda-windows_510": "Flake",
                "main_nightly_deployment_prototype_438": "Failed",
                "pull_requests-conda-windows_529": "Flake",
                "main_nightly_deployment_prototype_439": "Flake"
            }
        },
        "python.algorithms.AbinsAdvancedParametersTest.AbinsAdvancedParametersTest": {
            "py/object": "datatable_helper.Combined_LTS_Problem_test_entry",
            "test_name": "python.algorithms.AbinsAdvancedParametersTest.AbinsAdvancedParametersTest",
            "agent_name": "Windows",
            "past_failed_outcome": {
                "main_nightly_deployment_prototype_433": "Flake"
            }
        },
        "python.functions.CompositePCRmagnetTest.CompositePCRmagnetTest": {
            "py/object": "datatable_helper.Combined_LTS_Problem_test_entry",
            "test_name": "python.functions.CompositePCRmagnetTest.CompositePCRmagnetTest",
            "agent_name": "Windows",
            "past_failed_outcome": {
                "main_nightly_deployment_prototype_433": "Flake"
            }
        },
        "TypesTest_DateAndTimeTest": {
            "py/object": "datatable_helper.Combined_LTS_Problem_test_entry",
            "test_name": "TypesTest_DateAndTimeTest",
            "agent_name": "Windows",
            "past_failed_outcome": {
                "pull_requests-conda-windows_479": "Failed"
            }
        },
        "python.MuonQt5.tf_asymmetry_fitting_view_test.tf_asymmetry_fitting_view_test": {
            "py/object": "datatable_helper.Combined_LTS_Problem_test_entry",
            "test_name": "python.MuonQt5.tf_asymmetry_fitting_view_test.tf_asymmetry_fitting_view_test",
            "agent_name": "Windows",
            "past_failed_outcome": {
                "pull_requests-conda-windows_488": "Flake",
                "pull_requests-conda-windows_492": "Flake"
            }
        },
        "mantidqt_qt5.test_sliceviewer_imageinfowidget.test_sliceviewer_imageinfowidget": {
            "py/object": "datatable_helper.Combined_LTS_Problem_test_entry",
            "test_name": "mantidqt_qt5.test_sliceviewer_imageinfowidget.test_sliceviewer_imageinfowidget",
            "agent_name": "Windows",
            "past_failed_outcome": {
                "pull_requests-conda-windows_494": "Failed"
            }
        },
        "python.simplescanviewer.RectanglePlotTest.RectanglePlotTest": {
            "py/object": "datatable_helper.Combined_LTS_Problem_test_entry",
            "test_name": "python.simplescanviewer.RectanglePlotTest.RectanglePlotTest",
            "agent_name": "Windows",
            "past_failed_outcome": {
                "pull_requests-conda-windows_512": "Failed",
                "pull_requests-conda-windows_513": "Failed"
            }
        },
        "mantidqt_qt5.test_sample_shape.test_sample_shape": {
            "py/object": "datatable_helper.Combined_LTS_Problem_test_entry",
            "test_name": "mantidqt_qt5.test_sample_shape.test_sample_shape",
            "agent_name": "Windows",
            "past_failed_outcome": {
                "pull_requests-conda-windows_511": "Failed"
            }
        },
        "python.MuonQt5.model_fitting_view_test.model_fitting_view_test": {
            "py/object": "datatable_helper.Combined_LTS_Problem_test_entry",
            "test_name": "python.MuonQt5.model_fitting_view_test.model_fitting_view_test",
            "agent_name": "Windows",
            "past_failed_outcome": {
                "pull_requests-conda-windows_523": "Flake"
            }
        },
        "python.MuonQt5.background_corrections_model_test.background_corrections_model_test": {
            "py/object": "datatable_helper.Combined_LTS_Problem_test_entry",
            "test_name": "python.MuonQt5.background_corrections_model_test.background_corrections_model_test",
            "agent_name": "Windows",
            "past_failed_outcome": {
                "pull_requests-conda-windows_522": "Flake"
            }
        },
        "python.WorkflowAlgorithms.MolDynTest.MolDynTest": {
            "py/object": "datatable_helper.Combined_LTS_Problem_test_entry",
            "test_name": "python.WorkflowAlgorithms.MolDynTest.MolDynTest",
            "agent_name": "Windows",
            "past_failed_outcome": {
                "pull_requests-conda-windows_521": "Failed"
            }
        },
        "python.algorithms.IntegratePeaksSkewTest.IntegratePeaksSkewTest": {
            "py/object": "datatable_helper.Combined_LTS_Problem_test_entry",
            "test_name": "python.algorithms.IntegratePeaksSkewTest.IntegratePeaksSkewTest",
            "agent_name": "Windows",
            "past_failed_outcome": {
                "pull_requests-conda-windows_519": "Failed"
            }
        }
    }
}